audioldm/__init__.py
audioldm/__main__.py
audioldm/ldm.py
audioldm/pipeline.py
audioldm/utils.py
audioldm/audio/__init__.py
audioldm/audio/audio_processing.py
audioldm/audio/stft.py
audioldm/audio/tools.py
audioldm/clap/__init__.py
audioldm/clap/encoders.py
audioldm/clap/open_clip/__init__.py
audioldm/clap/open_clip/bert.py
audioldm/clap/open_clip/bpe_simple_vocab_16e6.txt.gz
audioldm/clap/open_clip/factory.py
audioldm/clap/open_clip/feature_fusion.py
audioldm/clap/open_clip/htsat.py
audioldm/clap/open_clip/linear_probe.py
audioldm/clap/open_clip/loss.py
audioldm/clap/open_clip/model.py
audioldm/clap/open_clip/openai.py
audioldm/clap/open_clip/pann_model.py
audioldm/clap/open_clip/pretrained.py
audioldm/clap/open_clip/timm_model.py
audioldm/clap/open_clip/tokenizer.py
audioldm/clap/open_clip/transform.py
audioldm/clap/open_clip/utils.py
audioldm/clap/open_clip/version.py
audioldm/clap/open_clip/model_configs/HTSAT-base.json
audioldm/clap/open_clip/model_configs/HTSAT-large.json
audioldm/clap/open_clip/model_configs/HTSAT-tiny-win-1536.json
audioldm/clap/open_clip/model_configs/HTSAT-tiny.json
audioldm/clap/open_clip/model_configs/PANN-10.json
audioldm/clap/open_clip/model_configs/PANN-14-fmax-18k.json
audioldm/clap/open_clip/model_configs/PANN-14-fmax-8k-20s.json
audioldm/clap/open_clip/model_configs/PANN-14-tiny-transformer.json
audioldm/clap/open_clip/model_configs/PANN-14-win-1536.json
audioldm/clap/open_clip/model_configs/PANN-14.json
audioldm/clap/open_clip/model_configs/PANN-6.json
audioldm/clap/open_clip/model_configs/RN101-quickgelu.json
audioldm/clap/open_clip/model_configs/RN101.json
audioldm/clap/open_clip/model_configs/RN50-quickgelu.json
audioldm/clap/open_clip/model_configs/RN50.json
audioldm/clap/open_clip/model_configs/RN50x16.json
audioldm/clap/open_clip/model_configs/RN50x4.json
audioldm/clap/open_clip/model_configs/ViT-B-16.json
audioldm/clap/open_clip/model_configs/ViT-B-32-quickgelu.json
audioldm/clap/open_clip/model_configs/ViT-B-32.json
audioldm-0.1.1.dist-info/LICENSE
audioldm-0.1.1.dist-info/METADATA
audioldm-0.1.1.dist-info/WHEEL
audioldm-0.1.1.dist-info/top_level.txt
audioldm-0.1.1.dist-info/RECORD
